wegnologyrest/__init__.py
wegnologyrest/application.py
wegnologyrest/application_api_token.py
wegnologyrest/application_api_tokens.py
wegnologyrest/application_certificate.py
wegnologyrest/application_certificate_authorities.py
wegnologyrest/application_certificate_authority.py
wegnologyrest/application_certificates.py
wegnologyrest/application_dashboard.py
wegnologyrest/application_dashboards.py
wegnologyrest/application_key.py
wegnologyrest/application_keys.py
wegnologyrest/application_template.py
wegnologyrest/application_templates.py
wegnologyrest/applications.py
wegnologyrest/audit_log.py
wegnologyrest/audit_logs.py
wegnologyrest/auth.py
wegnologyrest/client.py
wegnologyrest/dashboard.py
wegnologyrest/dashboards.py
wegnologyrest/data.py
wegnologyrest/data_table.py
wegnologyrest/data_table_row.py
wegnologyrest/data_table_rows.py
wegnologyrest/data_tables.py
wegnologyrest/device.py
wegnologyrest/device_recipe.py
wegnologyrest/device_recipes.py
wegnologyrest/devices.py
wegnologyrest/edge_deployment.py
wegnologyrest/edge_deployments.py
wegnologyrest/embedded_deployment.py
wegnologyrest/embedded_deployments.py
wegnologyrest/event.py
wegnologyrest/events.py
wegnologyrest/experience.py
wegnologyrest/experience_domain.py
wegnologyrest/experience_domains.py
wegnologyrest/experience_endpoint.py
wegnologyrest/experience_endpoints.py
wegnologyrest/experience_group.py
wegnologyrest/experience_groups.py
wegnologyrest/experience_slug.py
wegnologyrest/experience_slugs.py
wegnologyrest/experience_user.py
wegnologyrest/experience_users.py
wegnologyrest/experience_version.py
wegnologyrest/experience_versions.py
wegnologyrest/experience_view.py
wegnologyrest/experience_views.py
wegnologyrest/file.py
wegnologyrest/files.py
wegnologyrest/flow.py
wegnologyrest/flow_version.py
wegnologyrest/flow_versions.py
wegnologyrest/flows.py
wegnologyrest/instance.py
wegnologyrest/instance_api_token.py
wegnologyrest/instance_api_tokens.py
wegnologyrest/instance_custom_node.py
wegnology_rest-1.16.2.dist-info/LICENSE
wegnology_rest-1.16.2.dist-info/METADATA
wegnology_rest-1.16.2.dist-info/WHEEL
wegnology_rest-1.16.2.dist-info/top_level.txt
wegnology_rest-1.16.2.dist-info/RECORD
