Metadata-Version: 2.1
Name: wegnology-rest
Version: 1.16.2
Summary: A REST client for the WEGnology API
Home-page: https://github.com/WEGnology/wegnology-rest-python
Author: WEGnology
Author-email: hello@wegnology.com
License: MIT
Keywords: REST,WEGnology,IoT
Classifier: Development Status :: 4 - Beta
Classifier: Intended Audience :: Developers
Classifier: Operating System :: MacOS :: MacOS X
Classifier: Operating System :: Microsoft :: Windows
Classifier: Operating System :: POSIX
Classifier: Topic :: Communications
Classifier: Topic :: Internet
Classifier: Topic :: Software Development :: Libraries
Classifier: License :: OSI Approved :: MIT License
Classifier: Programming Language :: Python
Classifier: Programming Language :: Python :: 2.7
Classifier: Programming Language :: Python :: 3
License-File: LICENSE
Requires-Dist: requests (>=2.13)
